bloqade/analog/__init__.py
bloqade/analog/atom_arrangement.py
bloqade/analog/constants.py
bloqade/analog/factory.py
bloqade/analog/migrate.py
bloqade/analog/serialize.py
bloqade/analog/builder/__init__.py
bloqade/analog/builder/args.py
bloqade/analog/builder/assign.py
bloqade/analog/builder/base.py
bloqade/analog/builder/coupling.py
bloqade/analog/builder/drive.py
bloqade/analog/builder/field.py
bloqade/analog/builder/parallelize.py
bloqade/analog/builder/pragmas.py
bloqade/analog/builder/route.py
bloqade/analog/builder/sequence_builder.py
bloqade/analog/builder/spatial.py
bloqade/analog/builder/start.py
bloqade/analog/builder/typing.py
bloqade/analog/builder/waveform.py
bloqade/analog/builder/backend/__init__.py
bloqade/analog/builder/backend/bloqade.py
bloqade/analog/builder/backend/braket.py
bloqade/analog/builder/backend/quera.py
bloqade/analog/builder/parse/__init__.py
bloqade/analog/builder/parse/builder.py
bloqade/analog/builder/parse/stream.py
bloqade/analog/builder/parse/trait.py
bloqade/analog/compiler/__init__.py
bloqade/analog/compiler/analysis/__init__.py
bloqade/analog/compiler/analysis/common/__init__.py
bloqade/analog/compiler/analysis/common/assignment_scan.py
bloqade/analog/compiler/analysis/common/check_slices.py
bloqade/analog/compiler/analysis/common/is_constant.py
bloqade/analog/compiler/analysis/common/is_hyperfine.py
bloqade/analog/compiler/analysis/common/scan_channels.py
bloqade/analog/compiler/analysis/common/scan_variables.py
bloqade/analog/compiler/analysis/hardware/__init__.py
bloqade/analog/compiler/analysis/hardware/channels.py
bloqade/analog/compiler/analysis/hardware/lattice.py
bloqade/analog/compiler/analysis/hardware/piecewise_constant.py
bloqade/analog/compiler/analysis/hardware/piecewise_linear.py
bloqade/analog/compiler/analysis/python/__init__.py
bloqade/analog/compiler/analysis/python/waveform.py
bloqade/analog/compiler/codegen/__init__.py
bloqade/analog/compiler/codegen/common/__init__.py
bloqade_analog-0.16.8.dist-info/METADATA
bloqade_analog-0.16.8.dist-info/WHEEL
bloqade_analog-0.16.8.dist-info/licenses/LICENSE
bloqade_analog-0.16.8.dist-info/RECORD
