Metadata-Version: 2.4
Name: bloqade-analog
Version: 0.16.8
Summary: Analog neutral atom software development kit
Author-email: Roger-luo <rluo@quera.com>, kaihsin <khwu@quera.com>, weinbe58 <pweinberg@quera.com>, johnzl-777 <jlong@quera.com>
License: Apache License 2.0
License-File: LICENSE
Classifier: Development Status :: 3 - Alpha
Classifier: License :: OSI Approved :: Apache Software License
Classifier: Operating System :: OS Independent
Classifier: Programming Language :: Python
Classifier: Programming Language :: Python :: 3.10
Classifier: Programming Language :: Python :: 3.11
Classifier: Programming Language :: Python :: 3.12
Classifier: Programming Language :: Python :: 3.13
Requires-Python: <3.14,>=3.10
Requires-Dist: amazon-braket-sdk>=1.78.0
Requires-Dist: beartype>=0.15.0
Requires-Dist: bokeh>=3.2.2
Requires-Dist: juliacall>=0.9.14
Requires-Dist: numba>=0.61.0
Requires-Dist: numpy>=2.1.0
Requires-Dist: pandas>=2.1.0
Requires-Dist: plotext>=5.2.8
Requires-Dist: plum-dispatch>=2.2.2
Requires-Dist: pydantic>=2.0
Requires-Dist: requests-sigv4>=0.1.6
Requires-Dist: scipy>=1.0.0
Requires-Dist: simplejson>=3.19.1
Requires-Dist: tabulate>=0.9.0
